telesql/__init__.py
telesql/core.py
telesql/table.py
telesql/errors/__init__.py
telesql/types/__init__.py
telesql/types/sqltypes.py
telesql-0.2.3.dist-info/METADATA
telesql-0.2.3.dist-info/WHEEL
telesql-0.2.3.dist-info/top_level.txt
telesql-0.2.3.dist-info/RECORD
