Metadata-Version: 2.4
Name: telesql
Version: 0.2.3
Summary: Простая обёртка для MySQL в Telebot
Author: dap3842
License: MIT
Requires-Python: >=3.10
Requires-Dist: mysql-connector-python
